wingspan_gym-0.1.0.dist-info/METADATA
wingspan_gym-0.1.0.dist-info/WHEEL
wingspan_gym-0.1.0.dist-info/licenses/LICENSE
wingspan_gym/_internal/__init__.pyi
wingspan_gym/game.py
wingspan_gym/__init__.py
wingspan_gym/_internal.cpython-312-darwin.so
wingspan_gym-0.1.0.dist-info/RECORD
