Metadata-Version: 2.4
Name: wingspan_gym
Version: 0.1.0
Classifier: Programming Language :: Rust
Classifier: Programming Language :: Python :: Implementation :: CPython
Classifier: Programming Language :: Python :: Implementation :: PyPy
Requires-Dist: gymnasium >=1.0.0
License-File: LICENSE
Summary: Add your description here
Requires-Python: >=3.10
